[
    {
        "date": "2014-06-03T18:29:59.005Z",
        "latitude": -27.5950652,
        "longitude": -48.5479263
    },
    {
        "date": "2014-06-03T18:29:59.005Z",
        "latitude": -27.59372,
        "longitude": -48.5473623
    },
    {
        "date": "2014-06-03T18:29:59.005Z",
        "latitude": -27.5933658,
        "longitude": -48.5487128
    },
    {
        "date": "2014-06-03T18:29:59.005Z",
        "latitude": -27.5949423,
        "longitude": -48.5493436
    },
    {
        "date": "2014-06-03T18:29:59.005Z",
        "latitude": -27.5951629,
        "longitude": -48.5488216
    },
    {
        "date": "2014-06-03T18:29:59.005Z",
        "latitude": -27.5990126,
        "longitude": -48.5512757
    },
    {
        "date": "2014-06-03T18:29:59.005Z",
        "latitude": -27.6005843,
        "longitude": -48.5494564
    },
    {
        "date": "2014-06-03T18:29:59.005Z",
        "latitude": -27.6019747,
        "longitude": -48.5503678
    },
    {
        "date": "2014-06-03T18:29:59.005Z",
        "latitude": -27.6019529,
        "longitude": -48.5507742
    },
    {
        "date": "2014-06-03T18:29:59.005Z",
        "latitude": -27.6015901,
        "longitude": -48.5512194
    },
    {
        "date": "2014-06-03T18:29:59.005Z",
        "latitude": -27.5978253,
        "longitude": -48.5601504
    },
    {
        "date": "2014-06-03T18:29:59.005Z",
        "latitude": -27.5979049,
        "longitude": -48.5708626
    },
    {
        "date": "2014-06-03T18:29:59.005Z",
        "latitude": -27.5876887,
        "longitude": -48.6140377
    },
    {
        "date": "2014-06-03T18:29:59.005Z",
        "latitude": -27.6536204,
        "longitude": -48.67750760000001
    },
    {
        "date": "2014-06-03T18:29:59.005Z",
        "latitude": -27.6549066,
        "longitude": -48.678524
    },
    {
        "date": "2014-06-03T18:29:59.005Z",
        "latitude": -27.7976715,
        "longitude": -50.2946281
    },
    {
        "date": "2014-06-03T18:29:59.005Z",
        "latitude": -27.3743501,
        "longitude": -51.06679380000001
    },
    {
        "date": "2014-06-03T18:29:59.005Z",
        "latitude": -27.0972195,
        "longitude": -51.6525967
    },
    {
        "date": "2014-06-03T18:29:59.005Z",
        "latitude": -27.1720603,
        "longitude": -51.7377354
    },
    {
        "date": "2014-06-03T18:29:59.005Z",
        "latitude": -27.1810322,
        "longitude": -51.9180217
    },
    {
        "date": "2014-06-03T18:29:59.005Z",
        "latitude": -27.2238944,
        "longitude": -51.949699
    },
    {
        "date": "2014-06-03T18:29:59.005Z",
        "latitude": -27.2314992,
        "longitude": -52.0305122
    },
    {
        "date": "2014-06-03T18:29:59.005Z",
        "latitude": -27.1530889,
        "longitude": -52.3103863
    },
    {
        "date": "2014-06-03T18:29:59.005Z",
        "latitude": -27.1072901,
        "longitude": -52.6114295
    },
    {
        "date": "2014-06-03T18:29:59.005Z",
        "latitude": -27.099938,
        "longitude": -52.6134543
    },
    {
        "date": "2014-06-03T18:29:59.005Z",
        "latitude": -27.1003951,
        "longitude": -52.615597
    },
    {
        "date": "2014-06-03T18:29:59.005Z",
        "latitude": -27.1008435,
        "longitude": -52.615477
    },
    {
        "date": "2014-06-03T18:29:59.005Z",
        "latitude": -27.107756,
        "longitude": -52.6135447
    },
    {
        "date": "2014-06-03T18:29:59.005Z",
        "latitude": -27.1088552,
        "longitude": -52.6183497
    },
    {
        "date": "2014-06-03T18:29:59.005Z",
        "latitude": -27.2963347,
        "longitude": -52.6894641
    },
    {
        "date": "2014-06-03T18:29:59.005Z",
        "latitude": -27.2968667,
        "longitude": -52.6894354
    },
    {
        "date": "2014-06-03T18:29:59.005Z",
        "latitude": -27.549219,
        "longitude": -52.53617860000001
    },
    {
        "date": "2014-06-03T18:29:59.005Z",
        "latitude": -27.5513544,
        "longitude": -52.5264897
    },
    {
        "date": "2014-06-03T18:29:59.005Z",
        "latitude": -27.6222077,
        "longitude": -52.3799843
    },
    {
        "date": "2014-06-03T18:29:59.005Z",
        "latitude": -27.6217545,
        "longitude": -52.37360289999999
    },
    {
        "date": "2014-06-03T18:29:59.005Z",
        "latitude": -27.6406988,
        "longitude": -52.2950337
    },
    {
        "date": "2014-06-03T18:29:59.005Z",
        "latitude": -27.6677117,
        "longitude": -52.2911086
    },
    {
        "date": "2014-06-03T18:29:59.005Z",
        "latitude": -27.8974732,
        "longitude": -52.2138281
    },
    {
        "date": "2014-06-03T18:29:59.005Z",
        "latitude": -27.9519409,
        "longitude": -52.0144207
    },
    {
        "date": "2014-06-03T18:29:59.005Z",
        "latitude": -27.9524246,
        "longitude": -52.01156049999999
    },
    {
        "date": "2014-06-03T18:29:59.005Z",
        "latitude": -27.9353686,
        "longitude": -51.8280299
    },
    {
        "date": "2014-06-03T18:29:59.005Z",
        "latitude": -27.9492994,
        "longitude": -51.8043361
    },
    {
        "date": "2014-06-03T18:29:59.005Z",
        "latitude": -28.2238003,
        "longitude": -51.6108248
    },
    {
        "date": "2014-06-03T18:29:59.005Z",
        "latitude": -28.2238468,
        "longitude": -51.6108625
    },
    {
        "date": "2014-06-03T18:29:59.005Z",
        "latitude": -28.2239011,
        "longitude": -51.6098831
    },
    {
        "date": "2014-06-03T18:29:59.005Z",
        "latitude": -28.2150994,
        "longitude": -51.549376
    },
    {
        "date": "2014-06-03T18:29:59.005Z",
        "latitude": -28.2117062,
        "longitude": -51.54323979999999
    },
    {
        "date": "2014-06-03T18:29:59.005Z",
        "latitude": -28.225821,
        "longitude": -51.5073946
    },
    {
        "date": "2014-06-03T18:29:59.005Z",
        "latitude": -28.2258626,
        "longitude": -51.5073577
    },
    {
        "date": "2014-06-03T18:29:59.005Z",
        "latitude": -28.2259072,
        "longitude": -51.5071288
    },
    {
        "date": "2014-06-03T18:29:59.005Z",
        "latitude": -28.5090976,
        "longitude": -50.9291786
    },
    {
        "date": "2014-06-03T18:29:59.005Z",
        "latitude": -28.5009908,
        "longitude": -50.9198974
    },
    {
        "date": "2014-06-03T18:29:59.005Z",
        "latitude": -28.791469,
        "longitude": -49.9846271
    },
    {
        "date": "2014-06-03T18:29:59.005Z",
        "latitude": -28.9278884,
        "longitude": -49.6821266
    },
    {
        "date": "2014-06-03T18:29:59.005Z",
        "latitude": -28.7478711,
        "longitude": -49.4745233
    },
    {
        "date": "2014-06-03T18:29:59.005Z",
        "latitude": -28.7516905,
        "longitude": -49.4729886
    },
    {
        "date": "2014-06-03T18:29:59.005Z",
        "latitude": -28.6982648,
        "longitude": -49.3995285
    },
    {
        "date": "2014-06-03T18:29:59.005Z",
        "latitude": -28.6796359,
        "longitude": -49.3719678
    },
    {
        "date": "2014-06-03T18:29:59.005Z",
        "latitude": -28.6773664,
        "longitude": -49.3741935
    },
    {
        "date": "2014-06-03T18:29:59.005Z",
        "latitude": -28.6757928,
        "longitude": -49.3722712
    },
    {
        "date": "2014-06-03T18:29:59.005Z",
        "latitude": -28.6743134,
        "longitude": -49.3738815
    },
    {
        "date": "2014-06-03T18:29:59.005Z",
        "latitude": -28.6732136,
        "longitude": -49.3726381
    },
    {
        "date": "2014-06-03T18:29:59.005Z",
        "latitude": -28.6726641,
        "longitude": -49.3732542
    },
    {
        "date": "2014-06-03T18:29:59.005Z",
        "latitude": -28.6732136,
        "longitude": -49.3726381
    },
    {
        "date": "2014-06-03T18:29:59.005Z",
        "latitude": -28.6736595,
        "longitude": -49.3731573
    },
    {
        "date": "2014-06-03T18:29:59.005Z",
        "latitude": -28.6768849,
        "longitude": -49.3696473
    },
    {
        "date": "2014-06-03T18:29:59.005Z",
        "latitude": -28.6756839,
        "longitude": -49.368211
    },
    {
        "date": "2014-06-03T18:29:59.005Z",
        "latitude": -28.6766083,
        "longitude": -49.3672146
    },
    {
        "date": "2014-06-03T18:29:59.005Z",
        "latitude": -28.6744946,
        "longitude": -49.3647867
    },
    {
        "date": "2014-06-03T18:29:59.005Z",
        "latitude": -28.6037246,
        "longitude": -49.3282615
    },
    {
        "date": "2014-06-03T18:29:59.005Z",
        "latitude": -28.5997158,
        "longitude": -49.3240344
    },
    {
        "date": "2014-06-03T18:29:59.005Z",
        "latitude": -28.5991255,
        "longitude": -49.3237602
    },
    {
        "date": "2014-06-03T18:29:59.005Z",
        "latitude": -28.3670406,
        "longitude": -49.2856862
    },
    {
        "date": "2014-06-03T18:29:59.005Z",
        "latitude": -28.3959718,
        "longitude": -49.3956495
    },
    {
        "date": "2014-06-03T18:29:59.005Z",
        "latitude": -28.3927202,
        "longitude": -49.3995973
    },
    {
        "date": "2014-06-03T18:29:59.005Z",
        "latitude": -28.232038,
        "longitude": -49.8254161
    },
    {
        "date": "2014-06-03T18:29:59.005Z",
        "latitude": -28.2876217,
        "longitude": -49.9336035
    },
    {
        "date": "2014-06-03T18:29:59.005Z",
        "latitude": -28.2913243,
        "longitude": -49.936603
    },
    {
        "date": "2014-06-03T18:29:59.005Z",
        "latitude": -28.289636,
        "longitude": -49.9395653
    },
    {
        "date": "2014-06-03T18:29:59.005Z",
        "latitude": -28.2914248,
        "longitude": -49.9427443
    },
    {
        "date": "2014-06-03T18:29:59.005Z",
        "latitude": -27.8265482,
        "longitude": -50.24997639999999
    },
    {
        "date": "2014-06-03T18:29:59.005Z",
        "latitude": -27.814995,
        "longitude": -50.278106
    },
    {
        "date": "2014-06-03T18:29:59.005Z",
        "latitude": -27.8153551,
        "longitude": -50.2827657
    },
    {
        "date": "2014-06-03T18:29:59.005Z",
        "latitude": -27.8106148,
        "longitude": -50.2930576
    },
    {
        "date": "2014-06-03T18:29:59.005Z",
        "latitude": -27.8092653,
        "longitude": -50.2933526
    },
    {
        "date": "2014-06-03T18:29:59.005Z",
        "latitude": -27.8109125,
        "longitude": -50.323342
    },
    {
        "date": "2014-06-03T18:29:59.005Z",
        "latitude": -27.8147877,
        "longitude": -50.3269289
    }
]